abasepy100.cpython-312-i386-linux-gnu.so
abasepy11-0.0.1.dist-info/METADATA
abasepy11-0.0.1.dist-info/LICENSE
abasepy11-0.0.1.dist-info/WHEEL
abasepy11-0.0.1.dist-info/RECORD
abasepy11-0.0.1.dist-info/top_level.txt
