Metadata-Version: 2.1
Name: abasepy11
Version: 0.0.1
License-File: LICENSE
Requires-Dist: pip
Requires-Dist: setuptools
Requires-Dist: langchain
Requires-Dist: sqlalchemy
Requires-Dist: pymysql
